class_serializer/__init__.py
class_serializer/serializable.py
class_serializer/serializable_test.py
class_serializer/test_models/__init__.py
class_serializer/test_models/bar.py
class_serializer/test_models/foo.py
class_serializer-0.0.6.dist-info/LICENSE
class_serializer-0.0.6.dist-info/METADATA
class_serializer-0.0.6.dist-info/WHEEL
class_serializer-0.0.6.dist-info/top_level.txt
class_serializer-0.0.6.dist-info/RECORD
