Metadata-Version: 2.1
Name: class-serializer
Version: 0.0.6
Summary: Serialize classes into JSON and vice-versa using simple annotations
Home-page: https://github.com/amamparo/python-class-serializer
Author: Aaron Mamparo
Author-email: aaronmamparo@gmail.com
License: UNKNOWN
Platform: UNKNOWN
Classifier: Programming Language :: Python :: 3
Classifier: License :: OSI Approved :: MIT License
Classifier: Operating System :: OS Independent
Requires-Python: >= 3.7
